setup.py
TornRPC.egg-info/PKG-INFO
TornRPC.egg-info/SOURCES.txt
TornRPC.egg-info/dependency_links.txt
TornRPC.egg-info/requires.txt
TornRPC.egg-info/top_level.txt
tornrpc/__init__.py
tornrpc/client/__init__.py
tornrpc/server/__init__.py
tornrpc/server/handlers.py