Metadata-Version: 1.0
Name: TornRPC
Version: 1.0.4
Summary: A tornado RPC framework
Home-page: UNKNOWN
Author: Kyle Laplante
Author-email: kyle.laplante@gmail.com
License: UNKNOWN
Keywords: rpc tornado asynchronous web
Platform: UNKNOWN
